MANIFEST.in
README.rst
setup.cfg
setup.py
cno/__init__.py
cno.egg-info/PKG-INFO
cno.egg-info/SOURCES.txt
cno.egg-info/dependency_links.txt
cno.egg-info/entry_points.txt
cno.egg-info/not-zip-safe
cno.egg-info/requires.txt
cno.egg-info/top_level.txt
cno/admin/__init__.py
cno/admin/distribute.py
cno/admin/install.py
cno/apps/__init__.py
cno/apps/plotmodel.py
cno/boolean/__init__.py
cno/boolean/asp.py
cno/boolean/cnorbool.py
cno/boolean/cnordt.py
cno/boolean/cross_validation.py
cno/boolean/simulator.py
cno/boolean/steady.py
cno/boolean/steady_cont.py
cno/boolean/steady_cont_neg.py
cno/boolean/ternary.py
cno/core/__init__.py
cno/core/base.py
cno/core/fitness.py
cno/core/gtt.py
cno/core/models.py
cno/core/params.py
cno/core/report.py
cno/core/results.py
cno/core/standalone.py
cno/datasets/__init__.py
cno/datasets/cnodata.py
cno/datasets/EGFR-ErbB_PCB2009/__init__.py
cno/datasets/ExtLiverBMC2012/__init__.py
cno/datasets/ExtLiverPCB/__init__.py
cno/datasets/ExtLiverPriHuMCP2010/__init__.py
cno/datasets/HepG2CancerRes2011/__init__.py
cno/datasets/LiverDREAM/__init__.py
cno/datasets/LiverMSB2009/__init__.py
cno/datasets/TCellPCB2007/__init__.py
cno/datasets/ToyMMB/MD-ToyMMB.csv
cno/datasets/ToyMMB/PKN-ToyMMB.sif
cno/datasets/ToyMMB/PKN-ToyMMB.xml
cno/datasets/ToyMMB/README.rst
cno/datasets/ToyMMB/__init__.py
cno/datasets/ToyMMB/__init__.pyc
cno/datasets/ToyMMB_Feedback/__init__.py
cno/datasets/ToyMMB_FeedbackAnd/__init__.py
cno/datasets/ToyMMB_T2/__init__.py
cno/datasets/ToyMMB_added_link/__init__.py
cno/datasets/ToyMSB2009/__init__.py
cno/datasets/ToyPB/MD-ToyPB.csv
cno/datasets/ToyPB/PKN-ToyPB.sif
cno/datasets/ToyPB/PKN-ToyPB.xml
cno/datasets/ToyPB/PKN-ToyPB_shuffled.sif
cno/datasets/ToyPB/README.rst
cno/datasets/ToyPB/__init__.py
cno/datasets/ToyPB/__init__.pyc
cno/datasets/ToyPB_SBML/__init__.py
cno/datasets/ToyPB_True/__init__.py
cno/datasets/ToyPCB/__init__.py
cno/feeder/__init__.py
cno/feeder/feeder.py
cno/fuzzy/__init__.py
cno/fuzzy/cnofuzzy.py
cno/fuzzy/cnorfuzzy.py
cno/fuzzy/fuzzy.py
cno/io/__init__.py
cno/io/adj2sif.py
cno/io/cna.py
cno/io/cnograph.py
cno/io/eda.py
cno/io/mapback.py
cno/io/measurements.py
cno/io/metabolites.py
cno/io/midas.py
