Metadata-Version: 1.1
Name: cno
Version: 0.1.4
Summary: CNO (Cell Net Optimiser): Manipulate, Visualise and Optimise Biological Networks to Perturbation Data.
Home-page: ['http://pypi.python.org/pypi/cno']
Author: Thomas Cokelaer
Author-email: cokelaer@ebi.ac.uk
License: BSD
Download-URL: ['http://pypi.python.org/pypi/cno']
Keywords: CellNOpt,CellNOptR,CNO,Logical model,SBML,SIF,Boolean,ODE,Fuzzy,Optimisation,Protein Network
Platform: Linux
Platform: Unix
Platform: MacOsX
Platform: Windows
Classifier: Development Status :: 4 - Beta
Classifier: Intended Audience :: Developers
Classifier: Intended Audience :: Science/Research
Classifier: License :: OSI Approved :: BSD License
Classifier: Operating System :: OS Independent
Classifier: Programming Language :: Python :: 2.7
Classifier: Topic :: Software Development :: Libraries :: Python Modules
Classifier: Topic :: Scientific/Engineering :: Bio-Informatics
Classifier: Topic :: Scientific/Engineering :: Information Analysis
Classifier: Topic :: Scientific/Engineering :: Mathematics
Classifier: Topic :: Scientific/Engineering :: Physics
